README.md
setup.py
greenery/__init__.py
greenery/_version.py
greenery/fsm.py
greenery/fsm_test.py
greenery/lego.py
greenery/lego_test.py
tr_greenery.egg-info/PKG-INFO
tr_greenery.egg-info/SOURCES.txt
tr_greenery.egg-info/dependency_links.txt
tr_greenery.egg-info/top_level.txt